lab6/partise1-1/practise1-1.v
module adder (in1, in2, sum, overflow); 
input [2:0]in1, in2;
output [2:0] sum;
output overflow;
//in verilog
assign sum = in1 + in2;
assign overflow =
( in1[2] & in2[2] & ~sum[2] ) | /* two +ve operands, get -ve operand*/
(~in1[2] & ~in2[2] & sum[2] ); /* two -ve operands, get +ve operand*/
endmodule

module adderTb; //verilog
reg [2:0] in1,in2;
wire overflow;
wire [2:0] sum;
adder ua(in1,in2,sum,overflow);

initial begin
$dumpfile("partise1-1.vcd");  // 指定输出的波形文件名
$dumpvars;
{in1,in2} = 6'b0;
repeat(63) #10 {in1,in2} = {in1,in2} + 1;
#10 $finish;
end
endmodule

lab6/partise1-1/partise1-1.vcd
$date
	Wed Mar 26 14:36:04 2025
$end
$version
	Icarus Verilog
$end
$timescale
	1s
$end
$scope module adderTb $end
$var wire 3 ! sum [2:0] $end
$var wire 1 " overflow $end
$var reg 3 # in1 [2:0] $end
$var reg 3 $ in2 [2:0] $end
$scope module ua $end
$var wire 3 % in1 [2:0] $end
$var wire 3 & in2 [2:0] $end
$var wire 1 " overflow $end
$var wire 3 ' sum [2:0] $end
$upscope $end
$upscope $end
$enddefinitions $end
$comment Show the parameter values. $end
$dumpall
$end
#0
$dumpvars
b0 '
b0 &
b0 %
b0 $
b0 #
0"
b0 !
$end
#10
b1 !
b1 '
b1 $
b1 &
#20
b10 !
b10 '
b10 $
b10 &
#30
b11 !
b11 '
b11 $
b11 &
#40
0"
b100 !
b100 '
b100 $
b100 &
#50
b101 !
b101 '
b101 $
b101 &
#60
b110 !
b110 '
b110 $
b110 &
#70
b111 !
b111 '
b111 $
b111 &
#80
b1 #
b1 %
b1 !
b1 '
b0 $
b0 &
#90
b10 !
b10 '
b1 $
b1 &
#100
b11 !
b11 '
b10 $
b10 &
#110
1"
b100 !
b100 '
b11 $
b11 &
#120
0"
b101 !
b101 '
b100 $
b100 &
#130
b110 !
b110 '
b101 $
b101 &
#140
b111 !
b111 '
b110 $
b110 &
#150
b0 !
b0 '
b111 $
b111 &
#160
b10 #
b10 %
b10 !
b10 '
b0 $
b0 &
#170
b11 !
b11 '
b1 $
b1 &
#180
1"
b100 !
b100 '
b10 $
b10 &
#190
b101 !
b101 '
b11 $
b11 &
#200
0"
b110 !
b110 '
b100 $
b100 &
#210
b111 !
b111 '
b101 $
b101 &
#220
b0 !
b0 '
b110 $
b110 &
#230
b1 !
b1 '
b111 $
b111 &
#240
b11 #
b11 %
b11 !
b11 '
b0 $
b0 &
#250
1"
b100 !
b100 '
b1 $
b1 &
#260
b101 !
b101 '
b10 $
b10 &
#270
b110 !
b110 '
b11 $
b11 &
#280
0"
b111 !
b111 '
b100 $
b100 &
#290
b0 !
b0 '
b101 $
b101 &
#300
b1 !
b1 '
b110 $
b110 &
#310
b10 !
b10 '
b111 $
b111 &
#320
b100 #
b100 %
b100 !
b100 '
b0 $
b0 &
#330
b101 !
b101 '
b1 $
b1 &
#340
b110 !
b110 '
b10 $
b10 &
#350
b111 !
b111 '
b11 $
b11 &
#360
1"
b0 !
b0 '
b100 $
b100 &
#370
b1 !
b1 '
b101 $
b101 &
#380
b10 !
b10 '
b110 $
b110 &
#390
b11 !
b11 '
b111 $
b111 &
#400
0"
b101 #
b101 %
b101 !
b101 '
b0 $
b0 &
#410
b110 !
b110 '
b1 $
b1 &
#420
b111 !
b111 '
b10 $
b10 &
#430
b0 !
b0 '
b11 $
b11 &
#440
1"
b1 !
b1 '
b100 $
b100 &
#450
b10 !
b10 '
b101 $
b101 &
#460
b11 !
b11 '
b110 $
b110 &
#470
0"
b100 !
b100 '
b111 $
b111 &
#480
b110 #
b110 %
b110 !
b110 '
b0 $
b0 &
#490
b111 !
b111 '
b1 $
b1 &
#500
b0 !
b0 '
b10 $
b10 &
#510
b1 !
b1 '
b11 $
b11 &
#520
1"
b10 !
b10 '
b100 $
b100 &
#530
b11 !
b11 '
b101 $
b101 &
#540
0"
b100 !
b100 '
b110 $
b110 &
#550
b101 !
b101 '
b111 $
b111 &
#560
b111 #
b111 %
b111 !
b111 '
b0 $
b0 &
#570
b0 !
b0 '
b1 $
b1 &
#580
b1 !
b1 '
b10 $
b10 &
#590
b10 !
b10 '
b11 $
b11 &
#600
1"
b11 !
b11 '
b100 $
b100 &
#610
0"
b100 !
b100 '
b101 $
b101 &
#620
b101 !
b101 '
b110 $
b110 &
#630
b110 !
b110 '
b111 $
b111 &
